cate_jl_ext/__init__.py
cate_jl_ext/_version.py
cate_jl_ext/config.py
cate_jl_ext/handlers/__init__.py
cate_jl_ext/handlers/labinfo.py
cate_jl_ext/handlers/server.py
cate_jl_ext/tests/__init__.py
cate_jl_ext/tests/test_handlers.py
cate_jl_ext-0.1.2.data/data/etc/jupyter/jupyter_notebook_config.d/cate_jl_ext.json
cate_jl_ext-0.1.2.data/data/etc/jupyter/jupyter_server_config.d/cate_jl_ext.json
cate_jl_ext-0.1.2.data/data/share/jupyter/labextensions/cate-jl-ext/build_log.json
cate_jl_ext-0.1.2.data/data/share/jupyter/labextensions/cate-jl-ext/package.json
cate_jl_ext-0.1.2.data/data/share/jupyter/labextensions/cate-jl-ext/schemas/cate-jl-ext/package.json.orig
cate_jl_ext-0.1.2.data/data/share/jupyter/labextensions/cate-jl-ext/schemas/cate-jl-ext/plugin.json
cate_jl_ext-0.1.2.data/data/share/jupyter/labextensions/cate-jl-ext/static/dfbe3b1e26a04e47ab737a831ddc4d455b8dde3af59ec7c9dc7c60200a6a3b45.png
cate_jl_ext-0.1.2.data/data/share/jupyter/labextensions/cate-jl-ext/static/lib_index_js.4711be543a7c8f4ac311.js
cate_jl_ext-0.1.2.data/data/share/jupyter/labextensions/cate-jl-ext/static/lib_index_js.4711be543a7c8f4ac311.js.map
cate_jl_ext-0.1.2.data/data/share/jupyter/labextensions/cate-jl-ext/static/remoteEntry.f7325f34392994ad297c.js
cate_jl_ext-0.1.2.data/data/share/jupyter/labextensions/cate-jl-ext/static/remoteEntry.f7325f34392994ad297c.js.map
cate_jl_ext-0.1.2.data/data/share/jupyter/labextensions/cate-jl-ext/static/style.js
cate_jl_ext-0.1.2.data/data/share/jupyter/labextensions/cate-jl-ext/static/style_index_js.f4b1071ddaafecc06b6b.js
cate_jl_ext-0.1.2.data/data/share/jupyter/labextensions/cate-jl-ext/static/style_index_js.f4b1071ddaafecc06b6b.js.map
cate_jl_ext-0.1.2.data/data/share/jupyter/labextensions/cate-jl-ext/static/vendors-node_modules_css-loader_dist_runtime_api_js-node_modules_css-loader_dist_runtime_cssW-7d5e6f.2d2b90ec6c229620ecb8.js
cate_jl_ext-0.1.2.dist-info/METADATA
cate_jl_ext-0.1.2.dist-info/WHEEL
cate_jl_ext-0.1.2.dist-info/licenses/LICENSE
cate_jl_ext-0.1.2.dist-info/RECORD
